Workbook

Sheet Sales_Data
A1: Date | B1: Month | C1: Quarter | D1: Year | E1: Region | F1: State/City | G1: Sales Executive Name | H1: Product Category | I1: Product Name | J1: Units Sold | K1: Selling Price | L1: Revenue | M1: Cost | N1: Profit | O1: Profit Margin % | P1: Customer Type | Q1: Sales Channel | R1: Target Sales | S1: Actual Sales | T1: Achievement % | U1: Growth % | V1: Previous Period Revenue (Reference)
A2: 45300 | B2: January | C2: Q1 | D2: 2024 | E2: West | F2: Pune | G2: Isha Bose | H2: Apparel | I2: Running Shoes | J2: 149 | K2: 7672.86 | L2: =J2*K2 -> 1143256.1 | M2: =L2*0.5673 -> 648569.21 | N2: =L2-M2 -> 494686.93 | O2: =IFERROR(N2/L2,0) -> 0.4327 | P2: New | Q2: Offline | R2: =L2/(1+-0.1362) -> 1323519.5 | S2: =L2 -> 1143256.1 | T2: =IFERROR(S2/R2,0) -> 0.8638 | U2: =IFERROR((L2-V2)/V2,0) -> 0.2892 | V2: =L2/1.2892 -> 886795.02
A3: 45308 | B3: January | C3: Q1 | D3: 2024 | E3: Central | F3: Raipur | G3: Karan Mehta | H3: Apparel | I3: Women's Kurti | J3: 25 | K3: 5299.36 | L3: =J3*K3 -> 132484 | M3: =L3*0.7392 -> 97932.173 | N3: =L3-M3 -> 34551.827 | O3: =IFERROR(N3/L3,0) -> 0.2608 | P3: Existing | Q3: Online | R3: =L3/(1+0.0976) -> 120703.35 | S3: =L3 -> 132484 | T3: =IFERROR(S3/R3,0) -> 1.0976 | U3: =IFERROR((L3-V3)/V3,0) -> -0.1386 | V3: =L3/0.8614 -> 153800.79
A4: 45310 | B4: January | C4: Q1 | D4: 2024 | E4: Central | F4: Raipur | G4: Nikhil Gupta | H4: Apparel | I4: Women's Kurti | J4: 20 | K4: 6479.14 | L4: =J4*K4 -> 129582.8 | M4: =L4*0.5913 -> 76622.31 | N4: =L4-M4 -> 52960.49 | O4: =IFERROR(N4/L4,0) -> 0.4087 | P4: Existing | Q4: Online | R4: =L4/(1+0.1587) -> 111834.64 | S4: =L4 -> 129582.8 | T4: =IFERROR(S4/R4,0) -> 1.1587 | U4: =IFERROR((L4-V4)/V4,0) -> 0.2551 | V4: =L4/1.2551 -> 103245
A5: 45310 | B5: January | C5: Q1 | D5: 2024 | E5: East | F5: Bhubaneswar | G5: Isha Bose | H5: Home Appliances | I5: Refrigerator 300L | J5: 77 | K5: 2350.9 | L5: =J5*K5 -> 181019.3 | M5: =L5*0.6207 -> 112358.68 | N5: =L5-M5 -> 68660.62 | O5: =IFERROR(N5/L5,0) -> 0.3793 | P5: New | Q5: Online | R5: =L5/(1+-0.0189) -> 184506.47 | S5: =L5 -> 181019.3 | T5: =IFERROR(S5/R5,0) -> 0.9811 | U5: =IFERROR((L5-V5)/V5,0) -> 0.236 | V5: =L5/1.236 -> 146455.74
A6: 45318 | B6: January | C6: Q1 | D6: 2024 | E6: East | F6: Bhubaneswar | G6: Vikram Rao | H6: FMCG | I6: Organic Tea | J6: 264 | K6: 7997.91 | L6: =J6*K6 -> 2111448.2 | M6: =L6*0.5934 -> 1252933.4 | N6: =L6-M6 -> 858514.85 | O6: =IFERROR(N6/L6,0) -> 0.4066 | P6: New | Q6: Offline | R6: =L6/(1+-0.0485) -> 2219073.3 | S6: =L6 -> 2111448.2 | T6: =IFERROR(S6/R6,0) -> 0.9515 | U6: =IFERROR((L6-V6)/V6,0) -> -0.1676 | V6: =L6/0.8324 -> 2536578.9
A7: 45321 | B7: January | C7: Q1 | D7: 2024 | E7: East | F7: Kolkata | G7: Karan Mehta | H7: FMCG | I7: Packaged Snacks | J7: 20 | K7: 6841.85 | L7: =J7*K7 -> 136837 | M7: =L7*0.572 -> 78270.764 | N7: =L7-M7 -> 58566.236 | O7: =IFERROR(N7/L7,0) -> 0.428 | P7: Existing | Q7: Offline | R7: =L7/(1+-0.0718) -> 147421.89 | S7: =L7 -> 136837 | T7: =IFERROR(S7/R7,0) -> 0.9282 | U7: =IFERROR((L7-V7)/V7,0) -> -0.146 | V7: =L7/0.854 -> 160230.68
A8: 45321 | B8: January | C8: Q1 | D8: 2024 | E8: South | F8: Hyderabad | G8: Priya Nair | H8: Home Appliances | I8: Refrigerator 300L | J8: 60 | K8: 3993.13 | L8: =J8*K8 -> 239587.8 | M8: =L8*0.702 -> 168190.64 | N8: =L8-M8 -> 71397.164 | O8: =IFERROR(N8/L8,0) -> 0.298 | P8: Existing | Q8: Online | R8: =L8/(1+0.0987) -> 218064.8 | S8: =L8 -> 239587.8 | T8: =IFERROR(S8/R8,0) -> 1.0987 | U8: =IFERROR((L8-V8)/V8,0) -> -0.1766 | V8: =L8/0.8234 -> 290973.77
A9: 45321 | B9: January | C9: Q1 | D9: 2024 | E9: South | F9: Bengaluru | G9: Isha Bose | H9: Home Appliances | I9: Washing Machine 7kg | J9: 26 | K9: 2191.73 | L9: =J9*K9 -> 56984.98 | M9: =L9*0.6233 -> 35518.738 | N9: =L9-M9 -> 21466.242 | O9: =IFERROR(N9/L9,0) -> 0.3767 | P9: Existing | Q9: Online | R9: =L9/(1+0.181) -> 48251.465 | S9: =L9 -> 56984.98 | T9: =IFERROR(S9/R9,0) -> 1.181 | U9: =IFERROR((L9-V9)/V9,0) -> 0.1636 | V9: =L9/1.1636 -> 48972.998
A10: 45325 | B10: February | C10: Q1 | D10: 2024 | E10: North | F10: Delhi | G10: Karan Mehta | H10: Apparel | I10: Women's Kurti | J10: 249 | K10: 7316.92 | L10: =J10*K10 -> 1821913.1 | M10: =L10*0.7086 -> 1291007.6 | N10: =L10-M10 -> 530905.47 | O10: =IFERROR(N10/L10,0) -> 0.2914 | P10: New | Q10: Online | R10: =L10/(1+-0.1612) -> 2172047.1 | S10: =L10 -> 1821913.1 | T10: =IFERROR(S10/R10,0) -> 0.8388 | U10: =IFERROR((L10-V10)/V10,0) -> -0.1323 | V10: =L10/0.8677 -> 2099703.9
A11: 45330 | B11: February | C11: Q1 | D11: 2024 | E11: North | F11: Lucknow | G11: Arjun Verma | H11: Home Appliances | I11: Microwave Oven | J11: 444 | K11: 7474.07 | L11: =J11*K11 -> 3318487.1 | M11: =L11*0.74 -> 2455680.4 | N11: =L11-M11 -> 862806.64 | O11: =IFERROR(N11/L11,0) -> 0.26 | P11: New | Q11: Online | R11: =L11/(1+-0.079) -> 3603134.7 | S11: =L11 -> 3318487.1 | T11: =IFERROR(S11/R11,0) -> 0.921 | U11: =IFERROR((L11-V11)/V11,0) -> 0.186 | V11: =L11/1.186 -> 2798049.8
A12: 45348 | B12: February | C12: Q1 | D12: 2024 | E12: East | F12: Kolkata | G12: Karan Mehta | H12: Apparel | I12: Running Shoes | J12: 199 | K12: 4326.23 | L12: =J12*K12 -> 860919.77 | M12: =L12*0.7428 -> 639491.21 | N12: =L12-M12 -> 221428.56 | O12: =IFERROR(N12/L12,0) -> 0.2572 | P12: New | Q12: Offline | R12: =L12/(1+0.0941) -> 786874.85 | S12: =L12 -> 860919.77 | T12: =IFERROR(S12/R12,0) -> 1.0941 | U12: =IFERROR((L12-V12)/V12,0) -> -0.1783 | V12: =L12/0.8217 -> 1047730
A13: 45350 | B13: February | C13: Q1 | D13: 2024 | E13: Central | F13: Raipur | G13: Vikram Rao | H13: FMCG | I13: Skin Care Cream | J13: 412 | K13: 2667.03 | L13: =J13*K13 -> 1098816.4 | M13: =L13*0.5187 -> 569956.05 | N13: =L13-M13 -> 528860.31 | O13: =IFERROR(N13/L13,0) -> 0.4813 | P13: New | Q13: Online | R13: =L13/(1+0.1812) -> 930254.28 | S13: =L13 -> 1098816.4 | T13: =IFERROR(S13/R13,0) -> 1.1812 | U13: =IFERROR((L13-V13)/V13,0) -> 0.1256 | V13: =L13/1.1256 -> 976205.01
A14: 45353 | B14: March | C14: Q1 | D14: 2024 | E14: Central | F14: Nagpur | G14: Ananya Iyer | H14: Home Appliances | I14: Microwave Oven | J14: 126 | K14: 6869.34 | L14: =J14*K14 -> 865536.84 | M14: =L14*0.5218 -> 451637.12 | N14: =L14-M14 -> 413899.72 | O14: =IFERROR(N14/L14,0) -> 0.4782 | P14: New | Q14: Offline | R14: =L14/(1+0.0704) -> 808610.65 | S14: =L14 -> 865536.84 | T14: =IFERROR(S14/R14,0) -> 1.0704 | U14: =IFERROR((L14-V14)/V14,0) -> 0.2121 | V14: =L14/1.2121 -> 714080.39
A15: 45371 | B15: March | C15: Q1 | D15: 2024 | E15: North | F15: Lucknow | G15: Ananya Iyer | H15: Home Appliances | I15: Washing Machine 7kg | J15: 488 | K15: 6916.09 | L15: =J15*K15 -> 3375051.9 | M15: =L15*0.5255 -> 1773589.8 | N15: =L15-M15 -> 1601462.1 | O15: =IFERROR(N15/L15,0) -> 0.4745 | P15: Existing | Q15: Online | R15: =L15/(1+0.1128) -> 3032936.7 | S15: =L15 -> 3375051.9 | T15: =IFERROR(S15/R15,0) -> 1.1128 | U15: =IFERROR((L15-V15)/V15,0) -> -0.1099 | V15: =L15/0.8901 -> 3791767.1
A16: 45386 | B16: April | C16: Q2 | D16: 2024 | E16: North | F16: Lucknow | G16: Sneha Kapoor | H16: Electronics | I16: Laptop Pro 14 | J16: 466 | K16: 1790.24 | L16: =J16*K16 -> 834251.84 | M16: =L16*0.746 -> 622351.87 | N16: =L16-M16 -> 211899.97 | O16: =IFERROR(N16/L16,0) -> 0.254 | P16: New | Q16: Offline | R16: =L16/(1+-0.1804) -> 1017876.8 | S16: =L16 -> 834251.84 | T16: =IFERROR(S16/R16,0) -> 0.8196 | U16: =IFERROR((L16-V16)/V16,0) -> 0.1563 | V16: =L16/1.1563 -> 721483.91
A17: 45388 | B17: April | C17: Q2 | D17: 2024 | E17: South | F17: Bengaluru | G17: Vikram Rao | H17: Electronics | I17: Laptop Pro 14 | J17: 254 | K17: 6748.62 | L17: =J17*K17 -> 1714149.5 | M17: =L17*0.6744 -> 1156022.4 | N17: =L17-M17 -> 558127.07 | O17: =IFERROR(N17/L17,0) -> 0.3256 | P17: Existing | Q17: Online | R17: =L17/(1+0.1607) -> 1476823.9 | S17: =L17 -> 1714149.5 | T17: =IFERROR(S17/R17,0) -> 1.1607 | U17: =IFERROR((L17-V17)/V17,0) -> 0.181 | V17: =L17/1.181 -> 1451439
A18: 45413 | B18: May | C18: Q2 | D18: 2024 | E18: East | F18: Bhubaneswar | G18: Karan Mehta | H18: FMCG | I18: Skin Care Cream | J18: 36 | K18: 6590.07 | L18: =J18*K18 -> 237242.52 | M18: =L18*0.6397 -> 151764.04 | N18: =L18-M18 -> 85478.48 | O18: =IFERROR(N18/L18,0) -> 0.3603 | P18: New | Q18: Online | R18: =L18/(1+-0.0285) -> 244202.29 | S18: =L18 -> 237242.52 | T18: =IFERROR(S18/R18,0) -> 0.9715 | U18: =IFERROR((L18-V18)/V18,0) -> -0.0039 | V18: =L18/0.9961 -> 238171.39
A19: 45426 | B19: May | C19: Q2 | D19: 2024 | E19: East | F19: Kolkata | G19: Nikhil Gupta | H19: FMCG | I19: Organic Tea | J19: 469 | K19: 5825.37 | L19: =J19*K19 -> 2732098.5 | M19: =L19*0.6296 -> 1720129.2 | N19: =L19-M19 -> 1011969.3 | O19: =IFERROR(N19/L19,0) -> 0.3704 | P19: Existing | Q19: Offline | R19: =L19/(1+0.086) -> 2515744.5 | S19: =L19 -> 2732098.5 | T19: =IFERROR(S19/R19,0) -> 1.086 | U19: =IFERROR((L19-V19)/V19,0) -> -0.0525 | V19: =L19/0.9475 -> 2883481.3
A20: 45427 | B20: May | C20: Q2 | D20: 2024 | E20: West | F20: Pune | G20: Karan Mehta | H20: Electronics | I20: Smart Watch | J20: 388 | K20: 462.89 | L20: =J20*K20 -> 179601.32 | M20: =L20*0.6762 -> 121446.41 | N20: =L20-M20 -> 58154.907 | O20: =IFERROR(N20/L20,0) -> 0.3238 | P20: New | Q20: Offline | R20: =L20/(1+0.1531) -> 155755.2 | S20: =L20 -> 179601.32 | T20: =IFERROR(S20/R20,0) -> 1.1531 | U20: =IFERROR((L20-V20)/V20,0) -> 0.0397 | V20: =L20/1.0397 -> 172743.41
A21: 45433 | B21: May | C21: Q2 | D21: 2024 | E21: West | F21: Mumbai | G21: Rohan Sharma | H21: FMCG | I21: Packaged Snacks | J21: 410 | K21: 4584.92 | L21: =J21*K21 -> 1879817.2 | M21: =L21*0.6689 -> 1257409.7 | N21: =L21-M21 -> 622407.47 | O21: =IFERROR(N21/L21,0) -> 0.3311 | P21: Existing | Q21: Offline | R21: =L21/(1+-0.1645) -> 2249930.8 | S21: =L21 -> 1879817.2 | T21: =IFERROR(S21/R21,0) -> 0.8355 | U21: =IFERROR((L21-V21)/V21,0) -> 0.2463 | V21: =L21/1.2463 -> 1508318.4
A22: 45438 | B22: May | C22: Q2 | D22: 2024 | E22: South | F22: Hyderabad | G22: Nikhil Gupta | H22: Home Appliances | I22: Microwave Oven | J22: 97 | K22: 5002.45 | L22: =J22*K22 -> 485237.65 | M22: =L22*0.5011 -> 243152.59 | N22: =L22-M22 -> 242085.06 | O22: =IFERROR(N22/L22,0) -> 0.4989 | P22: New | Q22: Offline | R22: =L22/(1+0.0325) -> 469963.83 | S22: =L22 -> 485237.65 | T22: =IFERROR(S22/R22,0) -> 1.0325 | U22: =IFERROR((L22-V22)/V22,0) -> -0.0313 | V22: =L22/0.9687 -> 500916.33
A23: 45439 | B23: May | C23: Q2 | D23: 2024 | E23: East | F23: Bhubaneswar | G23: Arjun Verma | H23: Home Appliances | I23: Washing Machine 7kg | J23: 348 | K23: 4934.57 | L23: =J23*K23 -> 1717230.4 | M23: =L23*0.6951 -> 1193646.8 | N23: =L23-M23 -> 523583.54 | O23: =IFERROR(N23/L23,0) -> 0.3049 | P23: Existing | Q23: Online | R23: =L23/(1+0.0794) -> 1590912 | S23: =L23 -> 1717230.4 | T23: =IFERROR(S23/R23,0) -> 1.0794 | U23: =IFERROR((L23-V23)/V23,0) -> 0.2772 | V23: =L23/1.2772 -> 1344527.4
A24: 45439 | B24: May | C24: Q2 | D24: 2024 | E24: Central | F24: Nagpur | G24: Sneha Kapoor | H24: Furniture | I24: Wooden Dining Table | J24: 112 | K24: 1817.16 | L24: =J24*K24 -> 203521.92 | M24: =L24*0.6038 -> 122886.54 | N24: =L24-M24 -> 80635.385 | O24: =IFERROR(N24/L24,0) -> 0.3962 | P24: New | Q24: Online | R24: =L24/(1+0.0977) -> 185407.6 | S24: =L24 -> 203521.92 | T24: =IFERROR(S24/R24,0) -> 1.0977 | U24: =IFERROR((L24-V24)/V24,0) -> 0.1117 | V24: =L24/1.1117 -> 183072.7
A25: 45449 | B25: June | C25: Q2 | D25: 2024 | E25: Central | F25: Bhopal | G25: Vikram Rao | H25: Furniture | I25: Sofa Set 3-Seater | J25: 163 | K25: 5562.66 | L25: =J25*K25 -> 906713.58 | M25: =L25*0.5157 -> 467592.19 | N25: =L25-M25 -> 439121.39 | O25: =IFERROR(N25/L25,0) -> 0.4843 | P25: Existing | Q25: Offline | R25: =L25/(1+0.0512) -> 862550.97 | S25: =L25 -> 906713.58 | T25: =IFERROR(S25/R25,0) -> 1.0512 | U25: =IFERROR((L25-V25)/V25,0) -> -0.0404 | V25: =L25/0.9596 -> 944887.02
A26: 45450 | B26: June | C26: Q2 | D26: 2024 | E26: West | F26: Ahmedabad | G26: Rohan Sharma | H26: Electronics | I26: Laptop Pro 14 | J26: 321 | K26: 5481.05 | L26: =J26*K26 -> 1759417.1 | M26: =L26*0.7029 -> 1236694.2 | N26: =L26-M26 -> 522722.81 | O26: =IFERROR(N26/L26,0) -> 0.2971 | P26: Existing | Q26: Online | R26: =L26/(1+0.0493) -> 1676753.1 | S26: =L26 -> 1759417.1 | T26: =IFERROR(S26/R26,0) -> 1.0493 | U26: =IFERROR((L26-V26)/V26,0) -> -0.0531 | V26: =L26/0.9469 -> 1858081.2
A27: 45455 | B27: June | C27: Q2 | D27: 2024 | E27: North | F27: Chandigarh | G27: Nikhil Gupta | H27: Apparel | I27: Men's Formal Shirt | J27: 48 | K27: 2041.47 | L27: =J27*K27 -> 97990.56 | M27: =L27*0.5639 -> 55256.877 | N27: =L27-M27 -> 42733.683 | O27: =IFERROR(N27/L27,0) -> 0.4361 | P27: Existing | Q27: Online | R27: =L27/(1+-0.0063) -> 98611.814 | S27: =L27 -> 97990.56 | T27: =IFERROR(S27/R27,0) -> 0.9937 | U27: =IFERROR((L27-V27)/V27,0) -> 0.1934 | V27: =L27/1.1934 -> 82110.407
A28: 45458 | B28: June | C28: Q2 | D28: 2024 | E28: East | F28: Patna | G28: Karan Mehta | H28: Electronics | I28: Smart Watch | J28: 199 | K28: 2835.29 | L28: =J28*K28 -> 564222.71 | M28: =L28*0.6927 -> 390837.07 | N28: =L28-M28 -> 173385.64 | O28: =IFERROR(N28/L28,0) -> 0.3073 | P28: New | Q28: Offline | R28: =L28/(1+0.0984) -> 513676.9 | S28: =L28 -> 564222.71 | T28: =IFERROR(S28/R28,0) -> 1.0984 | U28: =IFERROR((L28-V28)/V28,0) -> -0.1314 | V28: =L28/0.8686 -> 649577.15
A29: 45461 | B29: June | C29: Q2 | D29: 2024 | E29: Central | F29: Bhopal | G29: Vikram Rao | H29: Electronics | I29: Smart Watch | J29: 400 | K29: 7697.64 | L29: =J29*K29 -> 3079056 | M29: =L29*0.7356 -> 2264953.6 | N29: =L29-M29 -> 814102.41 | O29: =IFERROR(N29/L29,0) -> 0.2644 | P29: New | Q29: Online | R29: =L29/(1+0.1487) -> 2680470.1 | S29: =L29 -> 3079056 | T29: =IFERROR(S29/R29,0) -> 1.1487 | U29: =IFERROR((L29-V29)/V29,0) -> -0.1015 | V29: =L29/0.8985 -> 3426884.8
A30: 45465 | B30: June | C30: Q2 | D30: 2024 | E30: West | F30: Pune | G30: Rohan Sharma | H30: Furniture | I30: Wooden Dining Table | J30: 416 | K30: 5931.37 | L30: =J30*K30 -> 2467449.9 | M30: =L30*0.5765 -> 1422484.9 | N30: =L30-M30 -> 1044965 | O30: =IFERROR(N30/L30,0) -> 0.4235 | P30: New | Q30: Online | R30: =L30/(1+-0.0992) -> 2739176.2 | S30: =L30 -> 2467449.9 | T30: =IFERROR(S30/R30,0) -> 0.9008 | U30: =IFERROR((L30-V30)/V30,0) -> 0.0171 | V30: =L30/1.0171 -> 2425965.9
A31: 45465 | B31: June | C31: Q2 | D31: 2024 | E31: Central | F31: Bhopal | G31: Vikram Rao | H31: Furniture | I31: Sofa Set 3-Seater | J31: 396 | K31: 3476.49 | L31: =J31*K31 -> 1376690 | M31: =L31*0.7031 -> 967950.77 | N31: =L31-M31 -> 408739.27 | O31: =IFERROR(N31/L31,0) -> 0.2969 | P31: Existing | Q31: Offline | R31: =L31/(1+0.1182) -> 1231166.2 | S31: =L31 -> 1376690 | T31: =IFERROR(S31/R31,0) -> 1.1182 | U31: =IFERROR((L31-V31)/V31,0) -> -0.0545 | V31: =L31/0.9455 -> 1456044.5
A32: 45465 | B32: June | C32: Q2 | D32: 2024 | E32: North | F32: Lucknow | G32: Priya Nair | H32: Furniture | I32: Wooden Dining Table | J32: 152 | K32: 3681.84 | L32: =J32*K32 -> 559639.68 | M32: =L32*0.6314 -> 353356.49 | N32: =L32-M32 -> 206283.19 | O32: =IFERROR(N32/L32,0) -> 0.3686 | P32: New | Q32: Offline | R32: =L32/(1+-0.141) -> 651501.37 | S32: =L32 -> 559639.68 | T32: =IFERROR(S32/R32,0) -> 0.859 | U32: =IFERROR((L32-V32)/V32,0) -> 0.2936 | V32: =L32/1.2936 -> 432621.89
A33: 45471 | B33: June | C33: Q2 | D33: 2024 | E33: Central | F33: Nagpur | G33: Karan Mehta | H33: Home Appliances | I33: Refrigerator 300L | J33: 413 | K33: 6224.78 | L33: =J33*K33 -> 2570834.1 | M33: =L33*0.5881 -> 1511907.6 | N33: =L33-M33 -> 1058926.6 | O33: =IFERROR(N33/L33,0) -> 0.4119 | P33: New | Q33: Offline | R33: =L33/(1+-0.1423) -> 2997358.2 | S33: =L33 -> 2570834.1 | T33: =IFERROR(S33/R33,0) -> 0.8577 | U33: =IFERROR((L33-V33)/V33,0) -> -0.0661 | V33: =L33/0.9339 -> 2752793.8
A34: 45472 | B34: June | C34: Q2 | D34: 2024 | E34: Central | F34: Nagpur | G34: Priya Nair | H34: FMCG | I34: Organic Tea | J34: 269 | K34: 6029.78 | L34: =J34*K34 -> 1622010.8 | M34: =L34*0.5186 -> 841174.81 | N34: =L34-M34 -> 780836.01 | O34: =IFERROR(N34/L34,0) -> 0.4814 | P34: New | Q34: Online | R34: =L34/(1+0.0081) -> 1608978.1 | S34: =L34 -> 1622010.8 | T34: =IFERROR(S34/R34,0) -> 1.0081 | U34: =IFERROR((L34-V34)/V34,0) -> -0.0735 | V34: =L34/0.9265 -> 1750686.3
A35: 45479 | B35: July | C35: Q3 | D35: 2024 | E35: Central | F35: Raipur | G35: Rohan Sharma | H35: FMCG | I35: Packaged Snacks | J35: 309 | K35: 2286.91 | L35: =J35*K35 -> 706655.19 | M35: =L35*0.549 -> 387953.7 | N35: =L35-M35 -> 318701.49 | O35: =IFERROR(N35/L35,0) -> 0.451 | P35: New | Q35: Offline | R35: =L35/(1+-0.1888) -> 871123.26 | S35: =L35 -> 706655.19 | T35: =IFERROR(S35/R35,0) -> 0.8112 | U35: =IFERROR((L35-V35)/V35,0) -> 0.0709 | V35: =L35/1.0709 -> 659870.38
A36: 45487 | B36: July | C36: Q3 | D36: 2024 | E36: Central | F36: Nagpur | G36: Arjun Verma | H36: Apparel | I36: Women's Kurti | J36: 83 | K36: 2849.49 | L36: =J36*K36 -> 236507.67 | M36: =L36*0.6248 -> 147769.99 | N36: =L36-M36 -> 88737.678 | O36: =IFERROR(N36/L36,0) -> 0.3752 | P36: New | Q36: Online | R36: =L36/(1+0.172) -> 201798.35 | S36: =L36 -> 236507.67 | T36: =IFERROR(S36/R36,0) -> 1.172 | U36: =IFERROR((L36-V36)/V36,0) -> 0.1589 | V36: =L36/1.1589 -> 204079.45
A37: 45489 | B37: July | C37: Q3 | D37: 2024 | E37: East | F37: Kolkata | G37: Nikhil Gupta | H37: Electronics | I37: Laptop Pro 14 | J37: 30 | K37: 1927.13 | L37: =J37*K37 -> 57813.9 | M37: =L37*0.6797 -> 39296.108 | N37: =L37-M37 -> 18517.792 | O37: =IFERROR(N37/L37,0) -> 0.3203 | P37: Existing | Q37: Online | R37: =L37/(1+0.0392) -> 55633.083 | S37: =L37 -> 57813.9 | T37: =IFERROR(S37/R37,0) -> 1.0392 | U37: =IFERROR((L37-V37)/V37,0) -> 0.0406 | V37: =L37/1.0406 -> 55558.236
A38: 45494 | B38: July | C38: Q3 | D38: 2024 | E38: West | F38: Pune | G38: Nikhil Gupta | H38: Home Appliances | I38: Refrigerator 300L | J38: 260 | K38: 5253.88 | L38: =J38*K38 -> 1366008.8 | M38: =L38*0.6619 -> 904161.22 | N38: =L38-M38 -> 461847.58 | O38: =IFERROR(N38/L38,0) -> 0.3381 | P38: New | Q38: Online | R38: =L38/(1+-0.0556) -> 1446430.3 | S38: =L38 -> 1366008.8 | T38: =IFERROR(S38/R38,0) -> 0.9444 | U38: =IFERROR((L38-V38)/V38,0) -> 0.0934 | V38: =L38/1.0934 -> 1249322.1
A39: 45499 | B39: July | C39: Q3 | D39: 2024 | E39: East | F39: Bhubaneswar | G39: Priya Nair | H39: Home Appliances | I39: Microwave Oven | J39: 453 | K39: 7438.71 | L39: =J39*K39 -> 3369735.6 | M39: =L39*0.647 -> 2180219 | N39: =L39-M39 -> 1189516.7 | O39: =IFERROR(N39/L39,0) -> 0.353 | P39: Existing | Q39: Offline | R39: =L39/(1+0.1472) -> 2937356.7 | S39: =L39 -> 3369735.6 | T39: =IFERROR(S39/R39,0) -> 1.1472 | U39: =IFERROR((L39-V39)/V39,0) -> 0.1626 | V39: =L39/1.1626 -> 2898448
A40: 45519 | B40: August | C40: Q3 | D40: 2024 | E40: North | F40: Chandigarh | G40: Priya Nair | H40: Electronics | I40: Smart Watch | J40: 150 | K40: 4362.13 | L40: =J40*K40 -> 654319.5 | M40: =L40*0.5897 -> 385852.21 | N40: =L40-M40 -> 268467.29 | O40: =IFERROR(N40/L40,0) -> 0.4103 | P40: Existing | Q40: Online | R40: =L40/(1+0.0492) -> 623636.58 | S40: =L40 -> 654319.5 | T40: =IFERROR(S40/R40,0) -> 1.0492 | U40: =IFERROR((L40-V40)/V40,0) -> -0.0545 | V40: =L40/0.9455 -> 692035.43
A41: 45520 | B41: August | C41: Q3 | D41: 2024 | E41: South | F41: Hyderabad | G41: Rohan Sharma | H41: Electronics | I41: Smart Watch | J41: 327 | K41: 2595.44 | L41: =J41*K41 -> 848708.88 | M41: =L41*0.6262 -> 531461.5 | N41: =L41-M41 -> 317247.38 | O41: =IFERROR(N41/L41,0) -> 0.3738 | P41: Existing | Q41: Offline | R41: =L41/(1+0.0069) -> 842892.92 | S41: =L41 -> 848708.88 | T41: =IFERROR(S41/R41,0) -> 1.0069 | U41: =IFERROR((L41-V41)/V41,0) -> 0.1183 | V41: =L41/1.1183 -> 758927.73
A42: 45527 | B42: August | C42: Q3 | D42: 2024 | E42: West | F42: Ahmedabad | G42: Divya Menon | H42: Home Appliances | I42: Refrigerator 300L | J42: 256 | K42: 6812.31 | L42: =J42*K42 -> 1743951.4 | M42: =L42*0.5835 -> 1017595.6 | N42: =L42-M42 -> 726355.74 | O42: =IFERROR(N42/L42,0) -> 0.4165 | P42: Existing | Q42: Offline | R42: =L42/(1+-0.1194) -> 1980412.6 | S42: =L42 -> 1743951.4 | T42: =IFERROR(S42/R42,0) -> 0.8806 | U42: =IFERROR((L42-V42)/V42,0) -> 0.2676 | V42: =L42/1.2676 -> 1375790
A43: 45531 | B43: August | C43: Q3 | D43: 2024 | E43: West | F43: Ahmedabad | G43: Rohan Sharma | H43: Home Appliances | I43: Washing Machine 7kg | J43: 206 | K43: 3882.53 | L43: =J43*K43 -> 799801.18 | M43: =L43*0.6124 -> 489798.24 | N43: =L43-M43 -> 310002.94 | O43: =IFERROR(N43/L43,0) -> 0.3876 | P43: New | Q43: Offline | R43: =L43/(1+-0.0759) -> 865492.02 | S43: =L43 -> 799801.18 | T43: =IFERROR(S43/R43,0) -> 0.9241 | U43: =IFERROR((L43-V43)/V43,0) -> -0.1712 | V43: =L43/0.8288 -> 965011.08
A44: 45531 | B44: August | C44: Q3 | D44: 2024 | E44: West | F44: Mumbai | G44: Ananya Iyer | H44: Electronics | I44: Smartphone X1 | J44: 173 | K44: 7922.11 | L44: =J44*K44 -> 1370525 | M44: =L44*0.5058 -> 693211.56 | N44: =L44-M44 -> 677313.47 | O44: =IFERROR(N44/L44,0) -> 0.4942 | P44: New | Q44: Online | R44: =L44/(1+-0.0193) -> 1397496.7 | S44: =L44 -> 1370525 | T44: =IFERROR(S44/R44,0) -> 0.9807 | U44: =IFERROR((L44-V44)/V44,0) -> -0.0392 | V44: =L44/0.9608 -> 1426441.5
A45: 45533 | B45: August | C45: Q3 | D45: 2024 | E45: South | F45: Bengaluru | G45: Vikram Rao | H45: Furniture | I45: Office Chair | J45: 380 | K45: 4691.33 | L45: =J45*K45 -> 1782705.4 | M45: =L45*0.6194 -> 1104207.7 | N45: =L45-M45 -> 678497.68 | O45: =IFERROR(N45/L45,0) -> 0.3806 | P45: New | Q45: Online | R45: =L45/(1+0.1805) -> 1510127.4 | S45: =L45 -> 1782705.4 | T45: =IFERROR(S45/R45,0) -> 1.1805 | U45: =IFERROR((L45-V45)/V45,0) -> -0.1672 | V45: =L45/0.8328 -> 2140616.5
A46: 45541 | B46: September | C46: Q3 | D46: 2024 | E46: North | F46: Lucknow | G46: Ananya Iyer | H46: Home Appliances | I46: Washing Machine 7kg | J46: 54 | K46: 3882.72 | L46: =J46*K46 -> 209666.88 | M46: =L46*0.7276 -> 152553.62 | N46: =L46-M46 -> 57113.258 | O46: =IFERROR(N46/L46,0) -> 0.2724 | P46: Existing | Q46: Online | R46: =L46/(1+-0.1273) -> 240250.81 | S46: =L46 -> 209666.88 | T46: =IFERROR(S46/R46,0) -> 0.8727 | U46: =IFERROR((L46-V46)/V46,0) -> 0.1874 | V46: =L46/1.1874 -> 176576.45
A47: 45546 | B47: September | C47: Q3 | D47: 2024 | E47: North | F47: Lucknow | G47: Nikhil Gupta | H47: Furniture | I47: Sofa Set 3-Seater | J47: 279 | K47: 2951.31 | L47: =J47*K47 -> 823415.49 | M47: =L47*0.7459 -> 614185.61 | N47: =L47-M47 -> 209229.88 | O47: =IFERROR(N47/L47,0) -> 0.2541 | P47: Existing | Q47: Offline | R47: =L47/(1+-0.1979) -> 1026574.6 | S47: =L47 -> 823415.49 | T47: =IFERROR(S47/R47,0) -> 0.8021 | U47: =IFERROR((L47-V47)/V47,0) -> -0.1242 | V47: =L47/0.8758 -> 940186.68
A48: 45550 | B48: September | C48: Q3 | D48: 2024 | E48: Central | F48: Nagpur | G48: Rohan Sharma | H48: FMCG | I48: Packaged Snacks | J48: 440 | K48: 3014.16 | L48: =J48*K48 -> 1326230.4 | M48: =L48*0.7413 -> 983134.6 | N48: =L48-M48 -> 343095.8 | O48: =IFERROR(N48/L48,0) -> 0.2587 | P48: New | Q48: Offline | R48: =L48/(1+-0.0696) -> 1425441.1 | S48: =L48 -> 1326230.4 | T48: =IFERROR(S48/R48,0) -> 0.9304 | U48: =IFERROR((L48-V48)/V48,0) -> 0.1701 | V48: =L48/1.1701 -> 1133433.4
A49: 45554 | B49: September | C49: Q3 | D49: 2024 | E49: East | F49: Bhubaneswar | G49: Sneha Kapoor | H49: Home Appliances | I49: Microwave Oven | J49: 63 | K49: 4302.31 | L49: =J49*K49 -> 271045.53 | M49: =L49*0.595 -> 161272.09 | N49: =L49-M49 -> 109773.44 | O49: =IFERROR(N49/L49,0) -> 0.405 | P49: New | Q49: Online | R49: =L49/(1+0.0807) -> 250805.52 | S49: =L49 -> 271045.53 | T49: =IFERROR(S49/R49,0) -> 1.0807 | U49: =IFERROR((L49-V49)/V49,0) -> -0.046 | V49: =L49/0.954 -> 284114.81
A50: 45557 | B50: September | C50: Q3 | D50: 2024 | E50: North | F50: Lucknow | G50: Nikhil Gupta | H50: Home Appliances | I50: Microwave Oven | J50: 252 | K50: 3602.11 | L50: =J50*K50 -> 907731.72 | M50: =L50*0.6905 -> 626788.75 | N50: =L50-M50 -> 280942.97 | O50: =IFERROR(N50/L50,0) -> 0.3095 | P50: Existing | Q50: Offline | R50: =L50/(1+-0.09) -> 997507.38 | S50: =L50 -> 907731.72 | T50: =IFERROR(S50/R50,0) -> 0.91 | U50: =IFERROR((L50-V50)/V50,0) -> 0.1926 | V50: =L50/1.1926 -> 761136.78
A51: 45559 | B51: September | C51: Q3 | D51: 2024 | E51: West | F51: Pune | G51: Nikhil Gupta | H51: FMCG | I51: Packaged Snacks | J51: 37 | K51: 1843.78 | L51: =J51*K51 -> 68219.86 | M51: =L51*0.5877 -> 40092.812 | N51: =L51-M51 -> 28127.048 | O51: =IFERROR(N51/L51,0) -> 0.4123 | P51: Existing | Q51: Online | R51: =L51/(1+0.1093) -> 61498.116 | S51: =L51 -> 68219.86 | T51: =IFERROR(S51/R51,0) -> 1.1093 | U51: =IFERROR((L51-V51)/V51,0) -> -0.1461 | V51: =L51/0.8539 -> 79892.095
A52: 45563 | B52: September | C52: Q3 | D52: 2024 | E52: Central | F52: Raipur | G52: Arjun Verma | H52: Apparel | I52: Men's Formal Shirt | J52: 30 | K52: 5209.58 | L52: =J52*K52 -> 156287.4 | M52: =L52*0.513 -> 80175.436 | N52: =L52-M52 -> 76111.964 | O52: =IFERROR(N52/L52,0) -> 0.487 | P52: New | Q52: Offline | R52: =L52/(1+0.1272) -> 138650.99 | S52: =L52 -> 156287.4 | T52: =IFERROR(S52/R52,0) -> 1.1272 | U52: =IFERROR((L52-V52)/V52,0) -> 0.065 | V52: =L52/1.065 -> 146748.73
A53: 45565 | B53: September | C53: Q3 | D53: 2024 | E53: West | F53: Mumbai | G53: Sneha Kapoor | H53: Apparel | I53: Men's Formal Shirt | J53: 303 | K53: 5163.04 | L53: =J53*K53 -> 1564401.1 | M53: =L53*0.6839 -> 1069893.9 | N53: =L53-M53 -> 494507.19 | O53: =IFERROR(N53/L53,0) -> 0.3161 | P53: Existing | Q53: Offline | R53: =L53/(1+0.1179) -> 1399410.6 | S53: =L53 -> 1564401.1 | T53: =IFERROR(S53/R53,0) -> 1.1179 | U53: =IFERROR((L53-V53)/V53,0) -> -0.1833 | V53: =L53/0.8167 -> 1915515
A54: 45567 | B54: October | C54: Q4 | D54: 2024 | E54: South | F54: Chennai | G54: Vikram Rao | H54: Electronics | I54: Wireless Earbuds | J54: 81 | K54: 1707.5 | L54: =J54*K54 -> 138307.5 | M54: =L54*0.5053 -> 69886.78 | N54: =L54-M54 -> 68420.72 | O54: =IFERROR(N54/L54,0) -> 0.4947 | P54: New | Q54: Online | R54: =L54/(1+0.1123) -> 124343.7 | S54: =L54 -> 138307.5 | T54: =IFERROR(S54/R54,0) -> 1.1123 | U54: =IFERROR((L54-V54)/V54,0) -> 0.2166 | V54: =L54/1.2166 -> 113683.63
A55: 45568 | B55: October | C55: Q4 | D55: 2024 | E55: West | F55: Ahmedabad | G55: Sneha Kapoor | H55: Electronics | I55: Wireless Earbuds | J55: 60 | K55: 1261.98 | L55: =J55*K55 -> 75718.8 | M55: =L55*0.6875 -> 52056.675 | N55: =L55-M55 -> 23662.125 | O55: =IFERROR(N55/L55,0) -> 0.3125 | P55: Existing | Q55: Online | R55: =L55/(1+0.0407) -> 72757.567 | S55: =L55 -> 75718.8 | T55: =IFERROR(S55/R55,0) -> 1.0407 | U55: =IFERROR((L55-V55)/V55,0) -> 0.2581 | V55: =L55/1.2581 -> 60185.041
A56: 45585 | B56: October | C56: Q4 | D56: 2024 | E56: North | F56: Delhi | G56: Nikhil Gupta | H56: Furniture | I56: Office Chair | J56: 484 | K56: 7814.71 | L56: =J56*K56 -> 3782319.6 | M56: =L56*0.6308 -> 2385887.2 | N56: =L56-M56 -> 1396432.4 | O56: =IFERROR(N56/L56,0) -> 0.3692 | P56: New | Q56: Online | R56: =L56/(1+0.0229) -> 3697643.6 | S56: =L56 -> 3782319.6 | T56: =IFERROR(S56/R56,0) -> 1.0229 | U56: =IFERROR((L56-V56)/V56,0) -> -0.161 | V56: =L56/0.839 -> 4508128.3
A57: 45593 | B57: October | C57: Q4 | D57: 2024 | E57: South | F57: Chennai | G57: Vikram Rao | H57: FMCG | I57: Skin Care Cream | J57: 397 | K57: 4172.32 | L57: =J57*K57 -> 1656411 | M57: =L57*0.5258 -> 870940.92 | N57: =L57-M57 -> 785470.12 | O57: =IFERROR(N57/L57,0) -> 0.4742 | P57: Existing | Q57: Offline | R57: =L57/(1+0.0037) -> 1650304.9 | S57: =L57 -> 1656411 | T57: =IFERROR(S57/R57,0) -> 1.0037 | U57: =IFERROR((L57-V57)/V57,0) -> -0.1144 | V57: =L57/0.8856 -> 1870382.8
A58: 45600 | B58: November | C58: Q4 | D58: 2024 | E58: East | F58: Bhubaneswar | G58: Sneha Kapoor | H58: FMCG | I58: Packaged Snacks | J58: 164 | K58: 1519.34 | L58: =J58*K58 -> 249171.76 | M58: =L58*0.7366 -> 183539.92 | N58: =L58-M58 -> 65631.842 | O58: =IFERROR(N58/L58,0) -> 0.2634 | P58: Existing | Q58: Offline | R58: =L58/(1+-0.1268) -> 285354.74 | S58: =L58 -> 249171.76 | T58: =IFERROR(S58/R58,0) -> 0.8732 | U58: =IFERROR((L58-V58)/V58,0) -> -0.125 | V58: =L58/0.875 -> 284767.73
A59: 45602 | B59: November | C59: Q4 | D59: 2024 | E59: West | F59: Pune | G59: Sneha Kapoor | H59: Furniture | I59: Sofa Set 3-Seater | J59: 38 | K59: 1261.42 | L59: =J59*K59 -> 47933.96 | M59: =L59*0.624 -> 29910.791 | N59: =L59-M59 -> 18023.169 | O59: =IFERROR(N59/L59,0) -> 0.376 | P59: New | Q59: Online | R59: =L59/(1+0.1821) -> 40549.835 | S59: =L59 -> 47933.96 | T59: =IFERROR(S59/R59,0) -> 1.1821 | U59: =IFERROR((L59-V59)/V59,0) -> -0.0315 | V59: =L59/0.9685 -> 49492.989
A60: 45609 | B60: November | C60: Q4 | D60: 2024 | E60: Central | F60: Bhopal | G60: Arjun Verma | H60: FMCG | I60: Packaged Snacks | J60: 119 | K60: 4357.56 | L60: =J60*K60 -> 518549.64 | M60: =L60*0.6293 -> 326323.29 | N60: =L60-M60 -> 192226.35 | O60: =IFERROR(N60/L60,0) -> 0.3707 | P60: New | Q60: Online | R60: =L60/(1+0.1416) -> 454230.59 | S60: =L60 -> 518549.64 | T60: =IFERROR(S60/R60,0) -> 1.1416 | U60: =IFERROR((L60-V60)/V60,0) -> 0.0582 | V60: =L60/1.0582 -> 490029.9
A61: 45610 | B61: November | C61: Q4 | D61: 2024 | E61: West | F61: Mumbai | G61: Isha Bose | H61: Apparel | I61: Women's Kurti | J61: 232 | K61: 5216.47 | L61: =J61*K61 -> 1210221 | M61: =L61*0.7411 -> 896894.81 | N61: =L61-M61 -> 313326.23 | O61: =IFERROR(N61/L61,0) -> 0.2589 | P61: Existing | Q61: Offline | R61: =L61/(1+-0.1367) -> 1401854.6 | S61: =L61 -> 1210221 | T61: =IFERROR(S61/R61,0) -> 0.8633 | U61: =IFERROR((L61-V61)/V61,0) -> -0.0908 | V61: =L61/0.9092 -> 1331083.4
A62: 45612 | B62: November | C62: Q4 | D62: 2024 | E62: North | F62: Chandigarh | G62: Sneha Kapoor | H62: Furniture | I62: Wooden Dining Table | J62: 235 | K62: 595.13 | L62: =J62*K62 -> 139855.55 | M62: =L62*0.5375 -> 75172.358 | N62: =L62-M62 -> 64683.192 | O62: =IFERROR(N62/L62,0) -> 0.4625 | P62: Existing | Q62: Online | R62: =L62/(1+0.1238) -> 124448.79 | S62: =L62 -> 139855.55 | T62: =IFERROR(S62/R62,0) -> 1.1238 | U62: =IFERROR((L62-V62)/V62,0) -> -0.1435 | V62: =L62/0.8565 -> 163287.27
A63: 45617 | B63: November | C63: Q4 | D63: 2024 | E63: East | F63: Kolkata | G63: Priya Nair | H63: Home Appliances | I63: Microwave Oven | J63: 168 | K63: 5089.54 | L63: =J63*K63 -> 855042.72 | M63: =L63*0.5715 -> 488656.91 | N63: =L63-M63 -> 366385.81 | O63: =IFERROR(N63/L63,0) -> 0.4285 | P63: New | Q63: Offline | R63: =L63/(1+0.1325) -> 755004.61 | S63: =L63 -> 855042.72 | T63: =IFERROR(S63/R63,0) -> 1.1325 | U63: =IFERROR((L63-V63)/V63,0) -> 0.017 | V63: =L63/1.017 -> 840749.97
A64: 45621 | B64: November | C64: Q4 | D64: 2024 | E64: Central | F64: Bhopal | G64: Karan Mehta | H64: Electronics | I64: Smartphone X1 | J64: 112 | K64: 2038.56 | L64: =J64*K64 -> 228318.72 | M64: =L64*0.5996 -> 136899.9 | N64: =L64-M64 -> 91418.815 | O64: =IFERROR(N64/L64,0) -> 0.4004 | P64: Existing | Q64: Offline | R64: =L64/(1+-0.1693) -> 274850.99 | S64: =L64 -> 228318.72 | T64: =IFERROR(S64/R64,0) -> 0.8307 | U64: =IFERROR((L64-V64)/V64,0) -> 0.0949 | V64: =L64/1.0949 -> 208529.29
A65: 45623 | B65: November | C65: Q4 | D65: 2024 | E65: South | F65: Chennai | G65: Sneha Kapoor | H65: Apparel | I65: Running Shoes | J65: 12 | K65: 2851.94 | L65: =J65*K65 -> 34223.28 | M65: =L65*0.6891 -> 23583.262 | N65: =L65-M65 -> 10640.018 | O65: =IFERROR(N65/L65,0) -> 0.3109 | P65: New | Q65: Online | R65: =L65/(1+-0.1458) -> 40064.716 | S65: =L65 -> 34223.28 | T65: =IFERROR(S65/R65,0) -> 0.8542 | U65: =IFERROR((L65-V65)/V65,0) -> 0.0065 | V65: =L65/1.0065 -> 34002.265
A66: 45623 | B66: November | C66: Q4 | D66: 2024 | E66: North | F66: Chandigarh | G66: Rohan Sharma | H66: FMCG | I66: Organic Tea | J66: 331 | K66: 4924.36 | L66: =J66*K66 -> 1629963.2 | M66: =L66*0.7127 -> 1161674.7 | N66: =L66-M66 -> 468288.42 | O66: =IFERROR(N66/L66,0) -> 0.2873 | P66: Existing | Q66: Online | R66: =L66/(1+-0.1503) -> 1918280.8 | S66: =L66 -> 1629963.2 | T66: =IFERROR(S66/R66,0) -> 0.8497 | U66: =IFERROR((L66-V66)/V66,0) -> 0.1421 | V66: =L66/1.1421 -> 1427163.3
A67: 45625 | B67: November | C67: Q4 | D67: 2024 | E67: West | F67: Ahmedabad | G67: Sneha Kapoor | H67: Home Appliances | I67: Washing Machine 7kg | J67: 497 | K67: 1417.12 | L67: =J67*K67 -> 704308.64 | M67: =L67*0.5769 -> 406315.65 | N67: =L67-M67 -> 297992.99 | O67: =IFERROR(N67/L67,0) -> 0.4231 | P67: New | Q67: Offline | R67: =L67/(1+0.124) -> 626609.11 | S67: =L67 -> 704308.64 | T67: =IFERROR(S67/R67,0) -> 1.124 | U67: =IFERROR((L67-V67)/V67,0) -> -0.0137 | V67: =L67/0.9863 -> 714091.7
A68: 45631 | B68: December | C68: Q4 | D68: 2024 | E68: North | F68: Chandigarh | G68: Sneha Kapoor | H68: Apparel | I68: Women's Kurti | J68: 244 | K68: 1784.96 | L68: =J68*K68 -> 435530.24 | M68: =L68*0.5057 -> 220247.64 | N68: =L68-M68 -> 215282.6 | O68: =IFERROR(N68/L68,0) -> 0.4943 | P68: New | Q68: Online | R68: =L68/(1+-0.0945) -> 480983.15 | S68: =L68 -> 435530.24 | T68: =IFERROR(S68/R68,0) -> 0.9055 | U68: =IFERROR((L68-V68)/V68,0) -> -0.0782 | V68: =L68/0.9218 -> 472478.02
A69: 45632 | B69: December | C69: Q4 | D69: 2024 | E69: West | F69: Pune | G69: Rohan Sharma | H69: Home Appliances | I69: Microwave Oven | J69: 456 | K69: 4840.25 | L69: =J69*K69 -> 2207154 | M69: =L69*0.5431 -> 1198705.3 | N69: =L69-M69 -> 1008448.7 | O69: =IFERROR(N69/L69,0) -> 0.4569 | P69: Existing | Q69: Online | R69: =L69/(1+-0.1772) -> 2682491.5 | S69: =L69 -> 2207154 | T69: =IFERROR(S69/R69,0) -> 0.8228 | U69: =IFERROR((L69-V69)/V69,0) -> 0.2381 | V69: =L69/1.2381 -> 1782694.5
A70: 45634 | B70: December | C70: Q4 | D70: 2024 | E70: East | F70: Patna | G70: Nikhil Gupta | H70: Electronics | I70: Smartphone X1 | J70: 121 | K70: 4000.83 | L70: =J70*K70 -> 484100.43 | M70: =L70*0.6992 -> 338483.02 | N70: =L70-M70 -> 145617.41 | O70: =IFERROR(N70/L70,0) -> 0.3008 | P70: New | Q70: Online | R70: =L70/(1+-0.1205) -> 550426.87 | S70: =L70 -> 484100.43 | T70: =IFERROR(S70/R70,0) -> 0.8795 | U70: =IFERROR((L70-V70)/V70,0) -> -0.1057 | V70: =L70/0.8943 -> 541317.71
A71: 45635 | B71: December | C71: Q4 | D71: 2024 | E71: West | F71: Pune | G71: Ananya Iyer | H71: Apparel | I71: Women's Kurti | J71: 359 | K71: 2090.86 | L71: =J71*K71 -> 750618.74 | M71: =L71*0.5082 -> 381464.44 | N71: =L71-M71 -> 369154.3 | O71: =IFERROR(N71/L71,0) -> 0.4918 | P71: Existing | Q71: Offline | R71: =L71/(1+-0.0282) -> 772400.43 | S71: =L71 -> 750618.74 | T71: =IFERROR(S71/R71,0) -> 0.9718 | U71: =IFERROR((L71-V71)/V71,0) -> 0.2511 | V71: =L71/1.2511 -> 599967.02
A72: 45637 | B72: December | C72: Q4 | D72: 2024 | E72: South | F72: Bengaluru | G72: Divya Menon | H72: Home Appliances | I72: Washing Machine 7kg | J72: 450 | K72: 344.18 | L72: =J72*K72 -> 154881 | M72: =L72*0.5547 -> 85912.491 | N72: =L72-M72 -> 68968.509 | O72: =IFERROR(N72/L72,0) -> 0.4453 | P72: New | Q72: Online | R72: =L72/(1+-0.0704) -> 166610.37 | S72: =L72 -> 154881 | T72: =IFERROR(S72/R72,0) -> 0.9296 | U72: =IFERROR((L72-V72)/V72,0) -> -0.0065 | V72: =L72/0.9935 -> 155894.31
A73: 45639 | B73: December | C73: Q4 | D73: 2024 | E73: Central | F73: Raipur | G73: Ananya Iyer | H73: Furniture | I73: Wooden Dining Table | J73: 48 | K73: 1351.84 | L73: =J73*K73 -> 64888.32 | M73: =L73*0.7184 -> 46615.769 | N73: =L73-M73 -> 18272.551 | O73: =IFERROR(N73/L73,0) -> 0.2816 | P73: New | Q73: Offline | R73: =L73/(1+-0.1355) -> 75058.785 | S73: =L73 -> 64888.32 | T73: =IFERROR(S73/R73,0) -> 0.8645 | U73: =IFERROR((L73-V73)/V73,0) -> 0.2829 | V73: =L73/1.2829 -> 50579.406
A74: 45645 | B74: December | C74: Q4 | D74: 2024 | E74: North | F74: Chandigarh | G74: Sneha Kapoor | H74: Home Appliances | I74: Washing Machine 7kg | J74: 323 | K74: 1835.61 | L74: =J74*K74 -> 592902.03 | M74: =L74*0.5139 -> 304692.35 | N74: =L74-M74 -> 288209.68 | O74: =IFERROR(N74/L74,0) -> 0.4861 | P74: Existing | Q74: Offline | R74: =L74/(1+0.0354) -> 572630.9 | S74: =L74 -> 592902.03 | T74: =IFERROR(S74/R74,0) -> 1.0354 | U74: =IFERROR((L74-V74)/V74,0) -> -0.0173 | V74: =L74/0.9827 -> 603339.81
A75: 45646 | B75: December | C75: Q4 | D75: 2024 | E75: North | F75: Delhi | G75: Ananya Iyer | H75: Apparel | I75: Women's Kurti | J75: 128 | K75: 6536.77 | L75: =J75*K75 -> 836706.56 | M75: =L75*0.5103 -> 426971.36 | N75: =L75-M75 -> 409735.2 | O75: =IFERROR(N75/L75,0) -> 0.4897 | P75: New | Q75: Online | R75: =L75/(1+0.0064) -> 831385.69 | S75: =L75 -> 836706.56 | T75: =IFERROR(S75/R75,0) -> 1.0064 | U75: =IFERROR((L75-V75)/V75,0) -> 0.1947 | V75: =L75/1.1947 -> 700348.67
A76: 45674 | B76: January | C76: Q1 | D76: 2025 | E76: South | F76: Bengaluru | G76: Isha Bose | H76: FMCG | I76: Packaged Snacks | J76: 212 | K76: 5836.23 | L76: =J76*K76 -> 1237280.8 | M76: =L76*0.5642 -> 698073.8 | N76: =L76-M76 -> 539206.96 | O76: =IFERROR(N76/L76,0) -> 0.4358 | P76: Existing | Q76: Offline | R76: =L76/(1+0.1039) -> 1120826.9 | S76: =L76 -> 1237280.8 | T76: =IFERROR(S76/R76,0) -> 1.1039 | U76: =IFERROR((L76-V76)/V76,0) -> -0.1598 | V76: =L76/0.8402 -> 1472602.7
A77: 45679 | B77: January | C77: Q1 | D77: 2025 | E77: North | F77: Chandigarh | G77: Priya Nair | H77: Furniture | I77: Wooden Dining Table | J77: 61 | K77: 2690.14 | L77: =J77*K77 -> 164098.54 | M77: =L77*0.666 -> 109289.63 | N77: =L77-M77 -> 54808.912 | O77: =IFERROR(N77/L77,0) -> 0.334 | P77: New | Q77: Online | R77: =L77/(1+0.1175) -> 146844.33 | S77: =L77 -> 164098.54 | T77: =IFERROR(S77/R77,0) -> 1.1175 | U77: =IFERROR((L77-V77)/V77,0) -> 0.0971 | V77: =L77/1.0971 -> 149574.82
A78: 45680 | B78: January | C78: Q1 | D78: 2025 | E78: East | F78: Kolkata | G78: Ananya Iyer | H78: Electronics | I78: Smart Watch | J78: 375 | K78: 2728.05 | L78: =J78*K78 -> 1023018.8 | M78: =L78*0.7222 -> 738824.14 | N78: =L78-M78 -> 284194.61 | O78: =IFERROR(N78/L78,0) -> 0.2778 | P78: New | Q78: Offline | R78: =L78/(1+0.0917) -> 937087.8 | S78: =L78 -> 1023018.8 | T78: =IFERROR(S78/R78,0) -> 1.0917 | U78: =IFERROR((L78-V78)/V78,0) -> 0.0417 | V78: =L78/1.0417 -> 982066.57
A79: 45686 | B79: January | C79: Q1 | D79: 2025 | E79: Central | F79: Raipur | G79: Priya Nair | H79: Apparel | I79: Women's Kurti | J79: 16 | K79: 3280.74 | L79: =J79*K79 -> 52491.84 | M79: =L79*0.5557 -> 29169.715 | N79: =L79-M79 -> 23322.125 | O79: =IFERROR(N79/L79,0) -> 0.4443 | P79: New | Q79: Online | R79: =L79/(1+-0.0131) -> 53188.611 | S79: =L79 -> 52491.84 | T79: =IFERROR(S79/R79,0) -> 0.9869 | U79: =IFERROR((L79-V79)/V79,0) -> -0.0018 | V79: =L79/0.9982 -> 52586.496
A80: 45687 | B80: January | C80: Q1 | D80: 2025 | E80: Central | F80: Bhopal | G80: Isha Bose | H80: Apparel | I80: Men's Formal Shirt | J80: 404 | K80: 1835.54 | L80: =J80*K80 -> 741558.16 | M80: =L80*0.7208 -> 534515.12 | N80: =L80-M80 -> 207043.04 | O80: =IFERROR(N80/L80,0) -> 0.2792 | P80: Existing | Q80: Offline | R80: =L80/(1+-0.0873) -> 812488.4 | S80: =L80 -> 741558.16 | T80: =IFERROR(S80/R80,0) -> 0.9127 | U80: =IFERROR((L80-V80)/V80,0) -> -0.0077 | V80: =L80/0.9923 -> 747312.47
A81: 45696 | B81: February | C81: Q1 | D81: 2025 | E81: Central | F81: Raipur | G81: Rohan Sharma | H81: FMCG | I81: Skin Care Cream | J81: 182 | K81: 7748.97 | L81: =J81*K81 -> 1410312.5 | M81: =L81*0.7448 -> 1050400.8 | N81: =L81-M81 -> 359911.76 | O81: =IFERROR(N81/L81,0) -> 0.2552 | P81: New | Q81: Online | R81: =L81/(1+-0.1701) -> 1699376.5 | S81: =L81 -> 1410312.5 | T81: =IFERROR(S81/R81,0) -> 0.8299 | U81: =IFERROR((L81-V81)/V81,0) -> -0.1967 | V81: =L81/0.8033 -> 1755648.6
A82: 45701 | B82: February | C82: Q1 | D82: 2025 | E82: Central | F82: Bhopal | G82: Vikram Rao | H82: Home Appliances | I82: Microwave Oven | J82: 265 | K82: 4771.01 | L82: =J82*K82 -> 1264317.6 | M82: =L82*0.7153 -> 904366.42 | N82: =L82-M82 -> 359951.23 | O82: =IFERROR(N82/L82,0) -> 0.2847 | P82: Existing | Q82: Offline | R82: =L82/(1+0.1804) -> 1071092.6 | S82: =L82 -> 1264317.6 | T82: =IFERROR(S82/R82,0) -> 1.1804 | U82: =IFERROR((L82-V82)/V82,0) -> 0.1477 | V82: =L82/1.1477 -> 1101609.9
A83: 45705 | B83: February | C83: Q1 | D83: 2025 | E83: North | F83: Delhi | G83: Isha Bose | H83: Electronics | I83: Wireless Earbuds | J83: 145 | K83: 5483.89 | L83: =J83*K83 -> 795164.05 | M83: =L83*0.6191 -> 492286.06 | N83: =L83-M83 -> 302877.99 | O83: =IFERROR(N83/L83,0) -> 0.3809 | P83: Existing | Q83: Online | R83: =L83/(1+-0.0229) -> 813800.07 | S83: =L83 -> 795164.05 | T83: =IFERROR(S83/R83,0) -> 0.9771 | U83: =IFERROR((L83-V83)/V83,0) -> 0.1772 | V83: =L83/1.1772 -> 675470.65
A84: 45712 | B84: February | C84: Q1 | D84: 2025 | E84: Central | F84: Nagpur | G84: Arjun Verma | H84: Furniture | I84: Sofa Set 3-Seater | J84: 385 | K84: 3319.52 | L84: =J84*K84 -> 1278015.2 | M84: =L84*0.5153 -> 658561.23 | N84: =L84-M84 -> 619453.97 | O84: =IFERROR(N84/L84,0) -> 0.4847 | P84: Existing | Q84: Offline | R84: =L84/(1+-0.0087) -> 1289231.5 | S84: =L84 -> 1278015.2 | T84: =IFERROR(S84/R84,0) -> 0.9913 | U84: =IFERROR((L84-V84)/V84,0) -> -0.0298 | V84: =L84/0.9702 -> 1317269.8
A85: 45720 | B85: March | C85: Q1 | D85: 2025 | E85: Central | F85: Bhopal | G85: Karan Mehta | H85: Apparel | I85: Women's Kurti | J85: 32 | K85: 1866.74 | L85: =J85*K85 -> 59735.68 | M85: =L85*0.5133 -> 30662.325 | N85: =L85-M85 -> 29073.355 | O85: =IFERROR(N85/L85,0) -> 0.4867 | P85: Existing | Q85: Online | R85: =L85/(1+0.1625) -> 51385.531 | S85: =L85 -> 59735.68 | T85: =IFERROR(S85/R85,0) -> 1.1625 | U85: =IFERROR((L85-V85)/V85,0) -> -0.1747 | V85: =L85/0.8253 -> 72380.565
A86: 45727 | B86: March | C86: Q1 | D86: 2025 | E86: South | F86: Bengaluru | G86: Ananya Iyer | H86: FMCG | I86: Packaged Snacks | J86: 360 | K86: 1036.08 | L86: =J86*K86 -> 372988.8 | M86: =L86*0.7242 -> 270118.49 | N86: =L86-M86 -> 102870.31 | O86: =IFERROR(N86/L86,0) -> 0.2758 | P86: Existing | Q86: Offline | R86: =L86/(1+-0.0027) -> 373998.6 | S86: =L86 -> 372988.8 | T86: =IFERROR(S86/R86,0) -> 0.9973 | U86: =IFERROR((L86-V86)/V86,0) -> -0.0004 | V86: =L86/0.9996 -> 373138.06
A87: 45728 | B87: March | C87: Q1 | D87: 2025 | E87: East | F87: Kolkata | G87: Rohan Sharma | H87: Apparel | I87: Running Shoes | J87: 454 | K87: 1342.17 | L87: =J87*K87 -> 609345.18 | M87: =L87*0.5907 -> 359940.2 | N87: =L87-M87 -> 249404.98 | O87: =IFERROR(N87/L87,0) -> 0.4093 | P87: Existing | Q87: Online | R87: =L87/(1+0.0642) -> 572585.21 | S87: =L87 -> 609345.18 | T87: =IFERROR(S87/R87,0) -> 1.0642 | U87: =IFERROR((L87-V87)/V87,0) -> -0.1122 | V87: =L87/0.8878 -> 686354.11
A88: 45735 | B88: March | C88: Q1 | D88: 2025 | E88: West | F88: Pune | G88: Karan Mehta | H88: Apparel | I88: Women's Kurti | J88: 201 | K88: 3672.89 | L88: =J88*K88 -> 738250.89 | M88: =L88*0.6636 -> 489903.29 | N88: =L88-M88 -> 248347.6 | O88: =IFERROR(N88/L88,0) -> 0.3364 | P88: New | Q88: Offline | R88: =L88/(1+-0.0522) -> 778909.99 | S88: =L88 -> 738250.89 | T88: =IFERROR(S88/R88,0) -> 0.9478 | U88: =IFERROR((L88-V88)/V88,0) -> -0.1092 | V88: =L88/0.8908 -> 828750.44
A89: 45744 | B89: March | C89: Q1 | D89: 2025 | E89: West | F89: Mumbai | G89: Nikhil Gupta | H89: Furniture | I89: Office Chair | J89: 281 | K89: 7850.9 | L89: =J89*K89 -> 2206102.9 | M89: =L89*0.6082 -> 1341751.8 | N89: =L89-M89 -> 864351.12 | O89: =IFERROR(N89/L89,0) -> 0.3918 | P89: Existing | Q89: Online | R89: =L89/(1+-0.0343) -> 2284459.9 | S89: =L89 -> 2206102.9 | T89: =IFERROR(S89/R89,0) -> 0.9657 | U89: =IFERROR((L89-V89)/V89,0) -> -0.193 | V89: =L89/0.807 -> 2733708.7
A90: 45747 | B90: March | C90: Q1 | D90: 2025 | E90: East | F90: Patna | G90: Priya Nair | H90: Furniture | I90: Wooden Dining Table | J90: 163 | K90: 4290.46 | L90: =J90*K90 -> 699344.98 | M90: =L90*0.7247 -> 506815.31 | N90: =L90-M90 -> 192529.67 | O90: =IFERROR(N90/L90,0) -> 0.2753 | P90: Existing | Q90: Offline | R90: =L90/(1+0.1712) -> 597118.32 | S90: =L90 -> 699344.98 | T90: =IFERROR(S90/R90,0) -> 1.1712 | U90: =IFERROR((L90-V90)/V90,0) -> 0.0778 | V90: =L90/1.0778 -> 648863.41
A91: 45752 | B91: April | C91: Q2 | D91: 2025 | E91: East | F91: Kolkata | G91: Priya Nair | H91: FMCG | I91: Packaged Snacks | J91: 434 | K91: 1287.43 | L91: =J91*K91 -> 558744.62 | M91: =L91*0.5251 -> 293396.8 | N91: =L91-M91 -> 265347.82 | O91: =IFERROR(N91/L91,0) -> 0.4749 | P91: Existing | Q91: Online | R91: =L91/(1+-0.1451) -> 653578.92 | S91: =L91 -> 558744.62 | T91: =IFERROR(S91/R91,0) -> 0.8549 | U91: =IFERROR((L91-V91)/V91,0) -> 0.0406 | V91: =L91/1.0406 -> 536944.67
A92: 45762 | B92: April | C92: Q2 | D92: 2025 | E92: East | F92: Bhubaneswar | G92: Arjun Verma | H92: Apparel | I92: Women's Kurti | J92: 108 | K92: 2863.23 | L92: =J92*K92 -> 309228.84 | M92: =L92*0.7413 -> 229231.34 | N92: =L92-M92 -> 79997.501 | O92: =IFERROR(N92/L92,0) -> 0.2587 | P92: New | Q92: Offline | R92: =L92/(1+-0.1095) -> 347253.05 | S92: =L92 -> 309228.84 | T92: =IFERROR(S92/R92,0) -> 0.8905 | U92: =IFERROR((L92-V92)/V92,0) -> 0.2264 | V92: =L92/1.2264 -> 252143.54
A93: 45764 | B93: April | C93: Q2 | D93: 2025 | E93: North | F93: Delhi | G93: Priya Nair | H93: Electronics | I93: Smart Watch | J93: 461 | K93: 2131.39 | L93: =J93*K93 -> 982570.79 | M93: =L93*0.6332 -> 622163.82 | N93: =L93-M93 -> 360406.97 | O93: =IFERROR(N93/L93,0) -> 0.3668 | P93: New | Q93: Online | R93: =L93/(1+-0.1679) -> 1180832.6 | S93: =L93 -> 982570.79 | T93: =IFERROR(S93/R93,0) -> 0.8321 | U93: =IFERROR((L93-V93)/V93,0) -> -0.0197 | V93: =L93/0.9803 -> 1002316.4
A94: 45765 | B94: April | C94: Q2 | D94: 2025 | E94: South | F94: Hyderabad | G94: Ananya Iyer | H94: Apparel | I94: Women's Kurti | J94: 149 | K94: 7703.48 | L94: =J94*K94 -> 1147818.5 | M94: =L94*0.6757 -> 775580.97 | N94: =L94-M94 -> 372237.55 | O94: =IFERROR(N94/L94,0) -> 0.3243 | P94: Existing | Q94: Online | R94: =L94/(1+0.0247) -> 1120150.8 | S94: =L94 -> 1147818.5 | T94: =IFERROR(S94/R94,0) -> 1.0247 | U94: =IFERROR((L94-V94)/V94,0) -> -0.0189 | V94: =L94/0.9811 -> 1169930.2
A95: 45766 | B95: April | C95: Q2 | D95: 2025 | E95: West | F95: Pune | G95: Ananya Iyer | H95: Electronics | I95: Smartphone X1 | J95: 17 | K95: 905.6 | L95: =J95*K95 -> 15395.2 | M95: =L95*0.5843 -> 8995.4154 | N95: =L95-M95 -> 6399.7846 | O95: =IFERROR(N95/L95,0) -> 0.4157 | P95: Existing | Q95: Offline | R95: =L95/(1+-0.105) -> 17201.341 | S95: =L95 -> 15395.2 | T95: =IFERROR(S95/R95,0) -> 0.895 | U95: =IFERROR((L95-V95)/V95,0) -> 0.1071 | V95: =L95/1.1071 -> 13905.88
A96: 45768 | B96: April | C96: Q2 | D96: 2025 | E96: Central | F96: Raipur | G96: Priya Nair | H96: Electronics | I96: Smartphone X1 | J96: 115 | K96: 1933.99 | L96: =J96*K96 -> 222408.85 | M96: =L96*0.5526 -> 122903.13 | N96: =L96-M96 -> 99505.719 | O96: =IFERROR(N96/L96,0) -> 0.4474 | P96: New | Q96: Offline | R96: =L96/(1+-0.1214) -> 253140.05 | S96: =L96 -> 222408.85 | T96: =IFERROR(S96/R96,0) -> 0.8786 | U96: =IFERROR((L96-V96)/V96,0) -> 0.0147 | V96: =L96/1.0147 -> 219186.8
A97: 45784 | B97: May | C97: Q2 | D97: 2025 | E97: East | F97: Bhubaneswar | G97: Nikhil Gupta | H97: Home Appliances | I97: Refrigerator 300L | J97: 273 | K97: 7172.28 | L97: =J97*K97 -> 1958032.4 | M97: =L97*0.6236 -> 1221029 | N97: =L97-M97 -> 737003.41 | O97: =IFERROR(N97/L97,0) -> 0.3764 | P97: Existing | Q97: Offline | R97: =L97/(1+-0.0952) -> 2164050 | S97: =L97 -> 1958032.4 | T97: =IFERROR(S97/R97,0) -> 0.9048 | U97: =IFERROR((L97-V97)/V97,0) -> 0.0225 | V97: =L97/1.0225 -> 1914946.2
A98: 45791 | B98: May | C98: Q2 | D98: 2025 | E98: North | F98: Delhi | G98: Ananya Iyer | H98: FMCG | I98: Packaged Snacks | J98: 60 | K98: 2790.93 | L98: =J98*K98 -> 167455.8 | M98: =L98*0.7481 -> 125273.68 | N98: =L98-M98 -> 42182.116 | O98: =IFERROR(N98/L98,0) -> 0.2519 | P98: Existing | Q98: Offline | R98: =L98/(1+0.1361) -> 147395.3 | S98: =L98 -> 167455.8 | T98: =IFERROR(S98/R98,0) -> 1.1361 | U98: =IFERROR((L98-V98)/V98,0) -> 0.2232 | V98: =L98/1.2232 -> 136899.77
A99: 45795 | B99: May | C99: Q2 | D99: 2025 | E99: West | F99: Mumbai | G99: Isha Bose | H99: Furniture | I99: Wooden Dining Table | J99: 164 | K99: 4619.13 | L99: =J99*K99 -> 757537.32 | M99: =L99*0.6229 -> 471870 | N99: =L99-M99 -> 285667.32 | O99: =IFERROR(N99/L99,0) -> 0.3771 | P99: New | Q99: Offline | R99: =L99/(1+0.1776) -> 643289.16 | S99: =L99 -> 757537.32 | T99: =IFERROR(S99/R99,0) -> 1.1776 | U99: =IFERROR((L99-V99)/V99,0) -> -0.1425 | V99: =L99/0.8575 -> 883425.45
A100: 45797 | B100: May | C100: Q2 | D100: 2025 | E100: South | F100: Chennai | G100: Ananya Iyer | H100: Home Appliances | I100: Microwave Oven | J100: 449 | K100: 2525.53 | L100: =J100*K100 -> 1133963 | M100: =L100*0.5412 -> 613700.76 | N100: =L100-M100 -> 520262.21 | O100: =IFERROR(N100/L100,0) -> 0.4588 | P100: New | Q100: Offline | R100: =L100/(1+0.1039) -> 1027233.4 | S100: =L100 -> 1133963 | T100: =IFERROR(S100/R100,0) -> 1.1039 | U100: =IFERROR((L100-V100)/V100,0) -> -0.1941 | V100: =L100/0.8059 -> 1407076.5
...

Sheet KPI_Summary
A1: Metric | B1: Value
A2: Total Revenue | B2: =SUM(Sales_Data!L2:L151) -> 1.4744626e+08
A3: Total Cost | B3: =SUM(Sales_Data!M2:M151) -> 92459619
A4: Total Profit | B4: =SUM(Sales_Data!N2:N151) -> 54986639
A5: Overall Profit Margin % | B5: =SUM(Sales_Data!N2:N151)/SUM(Sales_Data!L2:L151) -> 0.37292665
A6: Total Units Sold | B6: =SUM(Sales_Data!J2:J151) -> 35930
A7: Total Target Sales | B7: =SUM(Sales_Data!R2:R151) -> 1.4945793e+08
A8: Total Actual Sales | B8: =SUM(Sales_Data!S2:S151) -> 1.4744626e+08
A9: Overall Achievement % | B9: =SUM(Sales_Data!S2:S151)/SUM(Sales_Data!R2:R151) -> 0.98654024
A10: Average Growth % | B10: =AVERAGE(Sales_Data!U2:U151) -> 0.038638
